{
  "$schema": "../gen/schemas/desktop-schema.json",
  "identifier": "default",
  "description": "Capability for the main window",
  "windows": ["main"],
  "permissions": [
    "core:default",
    "opener:default",
    "fs:default",
    {
      "identifier": "fs:allow-read-dir",
      "allow": [
        { "path": "$RESOURCE/**" },
        { "path": "$APPDATA/**" },
        { "path": "/Users/jneaimimacmini/dev/apps/offers/**" }
      ]
    },
    {
      "identifier": "fs:allow-read-file",
      "allow": [
        { "path": "$RESOURCE/**" },
        { "path": "$APPDATA/**" },
        { "path": "/Users/jneaimimacmini/dev/apps/offers/**" }
      ]
    },
    {
      "identifier": "fs:allow-stat",
      "allow": [
        { "path": "$RESOURCE/**" },
        { "path": "$APPDATA/**" },
        { "path": "/Users/jneaimimacmini/dev/apps/offers/**" }
      ]
    },
    "shell:allow-open"
  ]
}
